bitvec-0.2.7.dist-info/METADATA
bitvec-0.2.7.dist-info/WHEEL
bitvec/alias/__init__.py
bitvec/arithm/__init__.pyi
bitvec/bitvec.pyi
bitvec/py.typed
bitvec/__init__.py
bitvec/bitvec.cp39-win_amd64.pyd
bitvec-0.2.7.dist-info/RECORD
