Metadata-Version: 2.1
Name: bitvec
Version: 0.2.7
Classifier: Programming Language :: Rust
Classifier: Programming Language :: Python :: Implementation :: CPython
Classifier: Programming Language :: Python :: Implementation :: PyPy
Summary: Fast & Simple bit manipulation library implemented in rust
Requires-Python: >=3.0
